prospr_core.cpython-313-darwin.so
prospr/_version.py
prospr/datasets.py
prospr/__init__.py
prospr/visualize.py
prospr/gen_data.py
prospr/helpers.py
prospr/core/core_module.cpp
prospr/core/src/depth_first_bnb.cpp
prospr/core/src/utils.cpp
prospr/core/src/depth_first.cpp
prospr/core/src/beam_search.cpp
prospr/core/src/amino_acid.hpp
prospr/core/src/protein.hpp
prospr/core/src/beam_search.hpp
prospr/core/src/amino_acid.cpp
prospr/core/src/protein.cpp
prospr/core/src/depth_first_bnb.hpp
prospr/core/src/utils.hpp
prospr/core/src/depth_first.hpp
prospr/data/replace_unfoldable.py
prospr/data/vanEck250/HP35.csv
prospr/data/vanEck250/HP20.csv
prospr/data/vanEck250/HP30.csv
prospr/data/vanEck250/HP25.csv
prospr/data/vanEck250/HP95.csv
prospr/data/vanEck250/HP80.csv
prospr/data/vanEck250/HP55.csv
prospr/data/vanEck250/HP100.csv
prospr/data/vanEck250/HP40.csv
prospr/data/vanEck250/HP50.csv
prospr/data/vanEck250/HP45.csv
prospr/data/vanEck250/HP90.csv
prospr/data/vanEck250/HP85.csv
prospr/data/vanEck250/HP60.csv
prospr/data/vanEck250/HP75.csv
prospr/data/vanEck250/HP65.csv
prospr/data/vanEck250/HP70.csv
prospr/data/vanEck250/HP15.csv
prospr/data/vanEck250/HP10.csv
prospr/data/vanEck_hratio/HP30_r0.8.csv
prospr/data/vanEck_hratio/HP30_r0.9.csv
prospr/data/vanEck_hratio/HP25_r1.0.csv
prospr/data/vanEck_hratio/HP10_r1.0.csv
prospr/data/vanEck_hratio/HP25_r0.2.csv
prospr/data/vanEck_hratio/HP20_r0.8.csv
prospr/data/vanEck_hratio/HP20_r0.9.csv
prospr/data/vanEck_hratio/HP10_r0.1.csv
prospr/data/vanEck_hratio/HP25_r0.3.csv
prospr/data/vanEck_hratio/HP25_r0.1.csv
prospr/data/vanEck_hratio/HP10_r0.3.csv
prospr/data/vanEck_hratio/HP15_r0.9.csv
prospr/data/vanEck_hratio/HP15_r0.8.csv
prospr/data/vanEck_hratio/HP10_r0.2.csv
prospr/data/vanEck_hratio/HP25_r0.4.csv
prospr/data/vanEck_hratio/HP10_r0.6.csv
prospr/data/vanEck_hratio/HP10_r0.7.csv
prospr/data/vanEck_hratio/HP25_r0.5.csv
prospr/data/vanEck_hratio/HP25_r0.7.csv
prospr-1.2.10.dist-info/RECORD
prospr-1.2.10.dist-info/WHEEL
prospr-1.2.10.dist-info/top_level.txt
prospr-1.2.10.dist-info/METADATA
prospr-1.2.10.dist-info/licenses/LICENSE
