Metadata-Version: 2.4
Name: prospr
Version: 1.2.10
Summary: A toolbox for protein folding with Python.
Author-email: okkevaneck <okke.van.eck@gmail.com>
License-Expression: LGPL-3.0-or-later
Project-URL: homepage, https://github.com/okkevaneck/prospr
Project-URL: documentation, https://prospr.readthedocs.io
Project-URL: repository, https://github.com/okkevaneck/prospr
Keywords: prospr,protein,structure,prediction,toolbox,python,c++,extension,pypi,package
Platform: Linux
Platform: macOS
Platform: Windows
Classifier: Development Status :: 5 - Production/Stable
Classifier: Programming Language :: Python :: 3
Classifier: Programming Language :: Python :: 3.9
Classifier: Programming Language :: Python :: 3.10
Classifier: Programming Language :: Python :: 3.11
Classifier: Programming Language :: Python :: 3.12
Classifier: Operating System :: OS Independent
Classifier: Topic :: Education
Classifier: Topic :: Scientific/Engineering
Classifier: Topic :: Scientific/Engineering :: Bio-Informatics
Requires-Python: >=3.9
License-File: LICENSE
Requires-Dist: matplotlib>=3.9.4
Requires-Dist: pandas>=2.2.3
Requires-Dist: seaborn>=0.12.2
Dynamic: license-file
